trove_dashboard/__init__.py
trove_dashboard/exceptions.py
trove_dashboard/version.py
trove_dashboard/api/__init__.py
trove_dashboard/api/trove.py
trove_dashboard/api/rest/__init__.py
trove_dashboard/api/rest/trove.py
trove_dashboard/content/__init__.py
trove_dashboard/content/backup_strategies/panel.py
trove_dashboard/content/backup_strategies/tables.py
trove_dashboard/content/backup_strategies/urls.py
trove_dashboard/content/backup_strategies/views.py
trove_dashboard/content/backup_strategies/templates/backup_strategies/_backup_strategy_help.html
trove_dashboard/content/backup_strategies/templates/backup_strategies/index.html
trove_dashboard/content/backup_strategies/workflows/__init__.py
trove_dashboard/content/backup_strategies/workflows/create_backup_strategy.py
trove_dashboard/content/database_backups/__init__.py
trove_dashboard/content/database_backups/panel.py
trove_dashboard/content/database_backups/tables.py
trove_dashboard/content/database_backups/tests.py
trove_dashboard/content/database_backups/urls.py
trove_dashboard/content/database_backups/views.py
trove_dashboard/content/database_backups/templates/database_backups/_backup_details_help.html
trove_dashboard/content/database_backups/templates/database_backups/backup.html
trove_dashboard/content/database_backups/templates/database_backups/details.html
trove_dashboard/content/database_backups/templates/database_backups/index.html
trove_dashboard/content/database_backups/workflows/__init__.py
trove_dashboard/content/database_backups/workflows/create_backup.py
trove_dashboard/content/database_clusters/__init__.py
trove_dashboard/content/database_clusters/cluster_manager.py
trove_dashboard/content/database_clusters/forms.py
trove_dashboard/content/database_clusters/panel.py
trove_dashboard/content/database_clusters/tables.py
trove_dashboard/content/database_clusters/tabs.py
trove_dashboard/content/database_clusters/tests.py
trove_dashboard/content/database_clusters/urls.py
trove_dashboard-25.0.0.dist-info/AUTHORS
trove_dashboard-25.0.0.dist-info/LICENSE
trove_dashboard-25.0.0.dist-info/METADATA
trove_dashboard-25.0.0.dist-info/WHEEL
trove_dashboard-25.0.0.dist-info/pbr.json
trove_dashboard-25.0.0.dist-info/top_level.txt
trove_dashboard-25.0.0.dist-info/RECORD
