Metadata-Version: 2.1
Name: trove-dashboard
Version: 25.0.0
Summary: Trove Management Dashboard
Home-page: https://docs.openstack.org/trove/latest
Author: OpenStack
Author-email: openstack-discuss@lists.openstack.org
License: Apache-2.0
Classifier: Environment :: OpenStack
Classifier: Intended Audience :: Information Technology
Classifier: Intended Audience :: System Administrators
Classifier: Operating System :: POSIX :: Linux
Classifier: Programming Language :: Python
Classifier: Programming Language :: Python :: Implementation :: CPython
Classifier: Programming Language :: Python :: 3 :: Only
Classifier: Programming Language :: Python :: 3
Classifier: Programming Language :: Python :: 3.9
Classifier: Programming Language :: Python :: 3.10
Classifier: Programming Language :: Python :: 3.11
Classifier: Programming Language :: Python :: 3.12
Requires-Python: >=3.9
License-File: LICENSE
License-File: AUTHORS
Requires-Dist: pbr >=1.6
Requires-Dist: oslo.log >=3.30.0
Requires-Dist: python-swiftclient >=2.2.0
Requires-Dist: python-troveclient >=1.2.0
Requires-Dist: horizon >=17.1.0
